snputils/__init__.py
snputils/_utils/data_home.py
snputils/_utils/download.py
snputils/_utils/plink.py
snputils/ancestry/__init__.py
snputils/ancestry/genobj/__init__.py
snputils/ancestry/genobj/base.py
snputils/ancestry/genobj/local.py
snputils/ancestry/genobj/wide.py
snputils/ancestry/io/__init__.py
snputils/ancestry/io/local/__init__.py
snputils/ancestry/io/local/others.py
snputils/ancestry/io/local/read/__init__.py
snputils/ancestry/io/local/read/auto.py
snputils/ancestry/io/local/read/base.py
snputils/ancestry/io/local/read/functional.py
snputils/ancestry/io/local/read/msp.py
snputils/ancestry/io/local/write/__init__.py
snputils/ancestry/io/local/write/adm_mapping_vcf.py
snputils/ancestry/io/local/write/base.py
snputils/ancestry/io/local/write/msp.py
snputils/ancestry/io/wide/__init__.py
snputils/ancestry/io/wide/read/__init__.py
snputils/ancestry/io/wide/read/admixture.py
snputils/ancestry/io/wide/read/base.py
snputils/ancestry/io/wide/read/functional.py
snputils/ancestry/io/wide/write/__init__.py
snputils/ancestry/io/wide/write/admixture.py
snputils/ancestry/io/wide/write/base.py
snputils/datasets/__init__.py
snputils/datasets/load_dataset.py
snputils/phenotype/__init__.py
snputils/phenotype/genobj/__init__.py
snputils/phenotype/genobj/multi_phenobj.py
snputils/phenotype/genobj/ukb_phenobj.py
snputils/phenotype/io/__init__.py
snputils/phenotype/io/read/__init__.py
snputils/phenotype/io/read/base.py
snputils/phenotype/io/read/multiPhenTabular.py
snputils/phenotype/io/read/ukbPhenReader.py
snputils/processing/__init__.py
snputils/processing/maasmds.py
snputils/processing/mdpca.py
snputils/processing/pca.py
snputils/processing/_utils/common.py
snputils/processing/_utils/gen_tools.py
snputils/processing/_utils/iterative_svd.py
snputils/processing/_utils/mds_distance.py
snputils/processing/_utils/solver.py
snputils/simulation/__init__.py
snputils/simulation/simulator_cli.py
snputils/simulation/pyadmix/__init__.py
snputils/simulation/pytorch/__init__.py
snputils-0.2.31.dist-info/licenses/LICENSE
snputils-0.2.31.dist-info/METADATA
snputils-0.2.31.dist-info/WHEEL
snputils-0.2.31.dist-info/entry_points.txt
snputils-0.2.31.dist-info/top_level.txt
snputils-0.2.31.dist-info/RECORD
