Metadata-Version: 2.4
Name: snputils
Version: 0.2.31
Summary: Process genomes with ease
License: BSD 3-Clause License
Project-URL: Homepage, https://snputils.org
Project-URL: Documentation, https://docs.snputils.org
Project-URL: Source Code, https://github.com/AI-sandbox/snputils
Project-URL: Issue Tracker, https://github.com/AI-sandbox/snputils/issues
Classifier: Development Status :: 2 - Pre-Alpha
Classifier: Intended Audience :: Science/Research
Classifier: Topic :: Scientific/Engineering
Classifier: License :: OSI Approved :: BSD License
Classifier: Programming Language :: Python :: 3.8
Classifier: Programming Language :: Python :: 3.9
Classifier: Programming Language :: Python :: 3.10
Classifier: Programming Language :: Python :: 3.11
Classifier: Programming Language :: Python :: 3.12
Classifier: Programming Language :: Python :: 3.13
Classifier: Programming Language :: Python :: 3.14
Requires-Python: >=3.8
License-File: LICENSE
Requires-Dist: numpy<2; python_version < "3.10"
Requires-Dist: numpy; python_version >= "3.10"
Requires-Dist: pandas
Requires-Dist: pandas-stubs
Requires-Dist: scikit-learn
Requires-Dist: scikit-allel
Requires-Dist: Pgenlib
Requires-Dist: matplotlib
Requires-Dist: joblib
Requires-Dist: tqdm
Requires-Dist: polars; python_version < "3.14"
Requires-Dist: polars-lts-cpu; python_version >= "3.14"
Requires-Dist: plotly
Requires-Dist: plotly_express
Requires-Dist: nbformat
Requires-Dist: adjustText
Requires-Dist: zstandard
Provides-Extra: gpu
Requires-Dist: torch; extra == "gpu"
Provides-Extra: demos
Requires-Dist: jupyterlab; extra == "demos"
Requires-Dist: seaborn; extra == "demos"
Provides-Extra: tests
Requires-Dist: tox; extra == "tests"
Requires-Dist: pytest; extra == "tests"
Requires-Dist: pytest-cov; extra == "tests"
Provides-Extra: docs
Requires-Dist: pdoc; extra == "docs"
Requires-Dist: torch; extra == "docs"
Provides-Extra: benchmark
Requires-Dist: pytest; extra == "benchmark"
Requires-Dist: pytest-benchmark; extra == "benchmark"
Requires-Dist: memory_profiler; extra == "benchmark"
Requires-Dist: pandas-plink; extra == "benchmark"
Requires-Dist: pysam; extra == "benchmark"
Requires-Dist: scikit-allel; extra == "benchmark"
Requires-Dist: sgkit[plink]; extra == "benchmark"
Requires-Dist: hail; extra == "benchmark"
Requires-Dist: pysnptools; extra == "benchmark"
Requires-Dist: Pgenlib; extra == "benchmark"
Requires-Dist: cyvcf2; extra == "benchmark"
Requires-Dist: plinkio; extra == "benchmark"
Requires-Dist: PyVCF3; extra == "benchmark"
Dynamic: license-file
